{
  "_metadata": {
        "name": "MGMT ACL Lab01",
        "weight": 1000,
        "description": "MGMT ACL for Lab1",
        "is_active": true,
        "config_context_schema": "",
        "location": "Lab01"
    },
  "mgmt_acl":
  {
  "name": "mgmt",
  "version": "0.0.2",
  "entries": [
    {
      "action": "permit",
      "destination": "any",
      "modifier": "",
      "name": "mgmt",
      "port": "",
      "protocol": "ip",
      "range": "",
      "remark": "",
      "sn": "",
      "source": "192.168.5.0/24"
    },
    {
      "action": "permit",
      "destination": "any",
      "modifier": "",
      "name": "mgmt",
      "port": "",
      "protocol": "ip",
      "range": "",
      "remark": "",
      "sn": "",
      "source": "192.168.6.0/24"
    },
    {
      "action": "permit",
      "destination": "any",
      "modifier": "",
      "name": "mgmt",
      "port": "",
      "protocol": "ip",
      "range": "",
      "remark": "",
      "sn": "",
      "source": "192.168.7.0/24"
    },
    {
      "action": "permit",
      "destination": "any",
      "modifier": "",
      "name": "mgmt",
      "port": "",
      "protocol": "ip",
      "range": "",
      "remark": "",
      "sn": "",
      "source": "192.168.2.0/24"
    },
    {
      "action": "permit",
      "destination": "any",
      "modifier": "",
      "name": "mgmt",
      "port": "",
      "protocol": "ip",
      "range": "",
      "remark": "",
      "sn": "",
      "source": "192.168.1.0/24"
    },
    {
      "action": "permit",
      "destination": "any",
      "modifier": "",
      "name": "mgmt",
      "port": "",
      "protocol": "icmp",
      "range": "",
      "remark": "",
      "sn": "",
      "source": "192.168.3.0/24"
    }
  ]
}
}
